{
  "id": "f9aa69e6af64c9b29bb1fe61179a048c",
  "source": "k8s_docs",
  "title": "Controllers — Design",
  "source_url": "https://kubernetes.io/docs/concepts/architecture/controller/#design",
  "text": "As a tenet of its design, Kubernetes uses lots of controllers that each manage\na particular aspect of cluster state. Most commonly, a particular control loop\n(controller) uses one kind of resource as its desired state, and has a different\nkind of resource that it manages to make that desired state happen. For example,\na controller for Jobs tracks Job objects (to discover new work) and Pod objects\n(to run the Jobs, and then to see when the work is finished). In this case\nsomething else creates the Jobs, whereas the Job controller creates Pods.\nIt's useful to have simple controllers rather than one, monolithic set of control\nloops that are interlinked. Controllers can fail, so Kubernetes is designed to\nallow for that.\nThere can be several controllers that create or update the same kind of object.\nBehind the scenes, Kubernetes controllers make sure that they only pay attention\nto the resources linked to their controlling resource.\nFor example, you can have Deployments and Jobs; these both create Pods.\nThe Job controller does not delete the Pods that your Deployment created,\nbecause there is information (\nlabels\n)\nthe controllers can use to tell those Pods apart."
}