{
  "id": "919b84ccb8af3088c0e993ed24e63af1",
  "source": "k8s_docs",
  "title": "GETTING STARTED — label",
  "source_url": "https://kubernetes.io/docs/reference/kubectl/kubectl-cmds/#label",
  "text": "Update pod 'foo' with the label 'unhealthy' and the value 'true'\nkubectl\nlabel\npods foo unhealthy=\ntrue\nUpdate pod 'foo' with the label 'status' and the value 'unhealthy', overwriting any existing value\nkubectl\nlabel\n--overwrite pods foo status=unhealthy\nUpdate all pods in the namespace\nkubectl\nlabel\npods --all status=unhealthy\nUpdate a pod identified by the type and name in \"pod.json\"\nkubectl\nlabel\n-f pod.json status=unhealthy\nUpdate pod 'foo' only if the resource is unchanged from version 1\nkubectl label pods foo\nstatus\n=unhealthy\n--resource-version\n=1\nUpdate pod 'foo' by removing a label named 'bar' if it exists # Does not require the --overwrite flag\nkubectl\nlabel\npods foo bar-\nUpdate the labels on a resource.\nA label key and value must begin with a letter or number, and may contain letters, numbers, hyphens, dots, and underscores, up to 63 characters each.\nOptionally, the key can begin with a DNS subdomain prefix and a single '/', like example.com/my-app.\nIf --overwrite is true, then existing labels can be overwritten, otherwise attempting to overwrite a label will result in an error.\nIf --resource-version is specified, then updates will use this resource version, otherwise the existing resource-version will be used.",
  "failure_classes": []
}