{
  "id": "dd01e123681244ebca1fab53ba4cb421",
  "source": "k8s_docs",
  "title": "Running Kubernetes Node Components as a Non-root User — kind",
  "source_url": "https://kubernetes.io/docs/tasks/administer-cluster/kubelet-in-userns/#kind",
  "text": "kind\nsupports running Kubernetes inside Rootless Docker or Rootless Podman.\nSee\nRunning kind with Rootless Docker\n.\n\nminikube\nalso supports running Kubernetes inside Rootless Docker or Rootless Podman.\nSee the Minikube documentation:\nRootless Docker\nRootless Podman\n\nSysbox\nis an open-source container runtime\n(similar to \"runc\") that supports running system-level workloads such as Docker\nand Kubernetes inside unprivileged containers isolated with the Linux user\nnamespace.\nSee\nSysbox Quick Start Guide: Kubernetes-in-Docker\nfor more info.\nSysbox supports running Kubernetes inside unprivileged containers without\nrequiring Cgroup v2 and without the\nKubeletInUserNamespace\nfeature gate. It\ndoes this by exposing specially crafted\n/proc\nand\n/sys\nfilesystems inside\nthe container plus several other advanced OS virtualization techniques.",
  "failure_classes": [
    "NodeNotReady"
  ]
}