{
  "id": "c7522f04f642608db8100c5763a97ecf",
  "source": "k8s_docs",
  "title": "Ephemeral Containers",
  "source_url": "https://kubernetes.io/docs/concepts/workloads/pods/ephemeral-containers/",
  "text": "This page provides an overview of ephemeral containers: a special type of container\nthat runs temporarily in an existing\nPod\nto\naccomplish user-initiated actions such as troubleshooting. You use ephemeral\ncontainers to inspect services rather than to build applications.\n\nPods\nare the fundamental building\nblock of Kubernetes applications. Since Pods are intended to be disposable and\nreplaceable, you cannot add a container to a Pod once it has been created.\nInstead, you usually delete and replace Pods in a controlled fashion using\ndeployments\n.\nSometimes it's necessary to inspect the state of an existing Pod, however, for\nexample to troubleshoot a hard-to-reproduce bug. In these cases you can run\nan ephemeral container in an existing Pod to inspect its state and run\narbitrary commands.",
  "failure_classes": []
}