{
  "id": "4593a3136d7f3c0dff5b58e6d3daade5",
  "source": "k8s_docs",
  "title": "Running in multiple zones — Node behavior",
  "source_url": "https://kubernetes.io/docs/setup/best-practices/multiple-zones/#node-behavior",
  "text": "Kubernetes automatically spreads the Pods for\nworkload resources (such as\nDeployment\nor\nStatefulSet\n)\nacross different nodes in a cluster. This spreading helps\nreduce the impact of failures.\nWhen nodes start up, the kubelet on each node automatically adds\nlabels\nto the Node object\nthat represents that specific kubelet in the Kubernetes API.\nThese labels can include\nzone information\n.\nIf your cluster spans multiple zones or regions, you can use node labels\nin conjunction with\nPod topology spread constraints\nto control how Pods are spread across your cluster among fault domains:\nregions, zones, and even specific nodes.\nThese hints enable the\nscheduler\nto place\nPods for better expected availability, reducing the risk that a correlated\nfailure affects your whole workload.\nFor example, you can set a constraint to make sure that the\n3 replicas of a StatefulSet are all running in different zones to each\nother, whenever that is feasible. You can define this declaratively\nwithout explicitly defining which availability zones are in use for\neach workload."
}