{
  "id": "374dc3dc88aa5fb76f5ada04d6c06ca7",
  "source": "k8s_docs",
  "title": "Scheduler Configuration — Multiple profiles",
  "source_url": "https://kubernetes.io/docs/reference/scheduling/config/#multiple-profiles",
  "text": "You can configure\nkube-scheduler\nto run more than one profile.\nEach profile has an associated scheduler name and can have a different set of\nplugins configured in its\nextension points\n.\nWith the following sample configuration, the scheduler will run with two\nprofiles: one with the default plugins and one with all scoring plugins\ndisabled.\napiVersion\n:\nkubescheduler.config.k8s.io/v1\nkind\n:\nKubeSchedulerConfiguration\nprofiles\n:\n-\nschedulerName\n:\ndefault-scheduler\n-\nschedulerName\n:\nno\n-\nscoring-scheduler\nplugins\n:\npreScore\n:\ndisabled\n:\n-\nname\n:\n'*'\nscore\n:\ndisabled\n:\n-\nname\n:\n'*'\nPods that want to be scheduled according to a specific profile can include\nthe corresponding scheduler name in its\n.spec.schedulerName\n.\nBy default, one profile with the scheduler name\ndefault-scheduler\nis created.\nThis profile includes the default plugins described above. When declaring more\nthan one profile, a unique scheduler name for each of them is required.\nIf a Pod doesn't specify a scheduler name, kube-apiserver will set it to\ndefault-scheduler\n. Therefore, a profile with this scheduler name should exist\nto get those pods scheduled.\nPod's scheduling events have\n.spec.schedulerName\nas their\nreportingController\n.\nEvents for leader election use the scheduler name of the first profile in the list.\nFor more information, please refer to the\nreportingController\nsection under\nEvent API Reference\n."
}