{
  "id": "4f1a8d2c41beb4fba6d4e3b4c0d1b60c",
  "source": "k8s_docs",
  "title": "",
  "source_url": "https://kubernetes.io/docs/reference/setup-tools/kubeadm/generated/kubeadm_init/kubeadm_init_phase_kubelet-finalize/",
  "text": "Synopsis\nUpdates settings relevant to the kubelet after TLS bootstrap\nkubeadm init phase kubelet-finalize [flags]\nExamples\n# Updates settings relevant to the kubelet after TLS bootstrap\n  kubeadm init phase kubelet-finalize all --config\nOptions\n-h, --help\nhelp for kubelet-finalize\nOptions inherited from parent commands\n--rootfs string\nThe path to the 'real' host root filesystem. This will cause kubeadm to chroot into the provided path.\nFeedback\nWas this page helpful?\nYes\nNo\nThanks for the feedback. If you have a specific, answerable question about how to use Kubernetes, ask it on\nStack Overflow\n.\nOpen an issue in the\nGitHub Repository\nif you want to\nreport a problem\nor\nsuggest an improvement\n.\nLast modified April 23, 2026 at 6:20 PM PST:\nUpdate kubeadm reference for v1.36.0 (46cbaf6ebd)"
}