{
  "id": "85de0e9a959e4f943945a3c35a2496f0",
  "source": "k8s_docs",
  "title": "Learning environment — minikube",
  "source_url": "https://kubernetes.io/docs/setup/learning-environment/#minikube",
  "text": "minikube\nruns a single-node Kubernetes cluster on your local machine. It supports multiple container runtimes and works on Linux, macOS, and Windows.\nTo get started with minikube, see the\nminikube Get Started\nguide.\n\nThere are several third-party tools that can also run Kubernetes locally. Kubernetes does not provide support for these tools, but they may work well for your learning needs:\nDocker Desktop\ncan run a local Kubernetes cluster\nPodman Desktop\ncan run a local Kubernetes cluster\nRancher Desktop\nprovides Kubernetes on your desktop\nMicroK8s\nruns a lightweight Kubernetes cluster\nRed Hat CodeReady Containers (CRC)\nruns a minimal OpenShift cluster locally (OpenShift is Kubernetes-conformant)\nRefer to each tool's documentation for setup instructions and support."
}