{
  "id": "bf65e027470f1bbc621d11d9141321f7",
  "source": "k8s_docs",
  "title": "Adopting Sidecar Containers — Automatic injection of sidecars",
  "source_url": "https://kubernetes.io/docs/tutorials/configuration/pod-sidecar-containers/#automatic-injection-of-sidecars",
  "text": "If you are using software that injects sidecars automatically,\nthere are a few possible strategies you may follow to\nensure that native sidecar containers can be used.\nAll strategies are generally options you may choose to decide whether\nthe Pod the sidecar will be injected to will land on a Node supporting the feature or not.\nAs an example, you can follow\nthis conversation in Istio community\n.\nThe discussion explores the options listed below.\nMark Pods that land to nodes supporting sidecars. You can use node labels\nand node affinity to mark nodes supporting sidecar containers and Pods landing on those nodes.\nCheck Nodes compatibility on injection. During sidecar injection, you may use\nthe following strategies to check node compatibility:\nquery node version and assume the feature gate is enabled on the version 1.29+\nquery node prometheus metrics and check feature enablement status\nassume the nodes are running with a\nsupported version skew\nfrom the API server\nthere may be other custom ways to detect nodes compatibility.\nDevelop a universal sidecar injector. The idea of a universal sidecar injector is to\ninject a sidecar container as a regular container as well as a native sidecar container.\nAnd have a runtime logic to decide which one will work. The universal sidecar injector\nis wasteful, as it will account for requests twice, but may be considered as a workable\nsolution for special cases.\nOne way would be on start of a native sidecar container\ndetect the node version and exit immediately if the version does not support the sidecar feature.\nConsider a runtime feature detection design:\nDefine an empty dir so containers can communicate with each other\nInject an init container, let's call it\nNativeSidecar\nwith\nrestartPolicy=Always\n.\nNativeSidecar\nmust write a file to an empty directory indicating the first run and exit\nimmediately with exit code\n0\n.\nNativeSidecar\non restart (when native sidecars are supported) checks that file already\nexists in the empty dir and changes it - indicating that the built-in sidecar containers\nare supported and running.\nInject regular container, let's call it\nOldWaySidecar\n.\nOldWaySidecar\non start checks the presence of a file in an empty dir.\nIf the file indicates that the\nNativeSidecar\nis NOT running, it assumes that the sidecar\nfeature is not supported and works assuming it is the sidecar.\nIf the file indicates that the\nNativeSidecar\nis running, it either does nothing and sleeps\nforever (in the case when Pod’s\nrestartPolicy=Always\n) or exits immediately with exit code\n0\n(in the case when Pod’s\nrestartPolicy!=Always\n).\nquery node version and assume the feature gate is enabled on the version 1.29+\nquery node prometheus metrics and check feature enablement status\nassume the nodes are running with a\nsupported version skew\nfrom the API server\nthere may be other custom ways to detect nodes compatibility.\nOne way would be on start of a native sidecar container\ndetect the node version and exit immediately if the version does not support the sidecar feature.\nConsider a runtime feature detection design:\nDefine an empty dir so containers can communicate with each other\nInject an init container, let's call it\nNativeSidecar\nwith\nrestartPolicy=Always\n.\nNativeSidecar\nmust write a file to an empty directory indicating the first run and exit\nimmediately with exit code\n0\n.\nNativeSidecar\non restart (when native sidecars are supported) checks that file already\nexists in the empty dir and changes it - indicating that the built-in sidecar containers\nare supported and running.\nInject regular container, let's call it\nOldWaySidecar\n.\nOldWaySidecar\non start checks the presence of a file in an empty dir.\nIf the file indicates that the\nNativeSidecar\nis NOT running, it assumes that the sidecar\nfeature is not supported and works assuming it is the sidecar.\nIf the file indicates that the\nNativeSidecar\nis running, it either does nothing and sleeps\nforever (in the case when Pod’s\nrestartPolicy=Always\n) or exits immediately with exit code\n0\n(in the case when Pod’s\nrestartPolicy!=Always\n).\nDefine an empty dir so containers can communicate with each other\nInject an init container, let's call it\nNativeSidecar\nwith\nrestartPolicy=Always\n.\nNativeSidecar\nmust write a file to an empty directory indicating the first run and exit\nimmediately with exit code\n0\n.\nNativeSidecar\non restart (when native sidecars are supported) checks that file already\nexists in the empty dir and changes it - indicating that the built-in sidecar containers\nare supported and running.\nInject regular container, let's call it\nOldWaySidecar\n.\nOldWaySidecar\non start checks the presence of a file in an empty dir.\nIf the file indicates that the\nNativeSidecar\nis NOT running, it assumes that the sidecar\nfeature is not supported and works assuming it is the sidecar.\nIf the file indicates that the\nNativeSidecar\nis running, it either does nothing and sleeps\nforever (in the case when Pod’s\nrestartPolicy=Always\n) or exits immediately with exit code\n0\n(in the case when Pod’s\nrestartPolicy!=Always\n)."
}