{
  "id": "dca9b0203ee06d4848f533d3bf8b4f9a",
  "source": "k8s_docs",
  "title": "Migrate from PodSecurityPolicy to the Built-In PodSecurity Admission Controller — Feedback",
  "source_url": "https://kubernetes.io/docs/tasks/configure-pod-container/migrate-from-psp/#feedback",
  "text": "Was this page helpful?\nThanks for the feedback. If you have a specific, answerable question about how to use Kubernetes, ask it on\nStack Overflow\n.\nOpen an issue in the\nGitHub Repository\nif you want to\nreport a problem\nor\nsuggest an improvement\n."
}