{
  "id": "56b8f301206c23658da8fe30edd8b457",
  "source": "k8s_docs",
  "title": "Apply Pod Security Standards at the Namespace Level — Feedback",
  "source_url": "https://kubernetes.io/docs/tutorials/security/ns-level-pss/#feedback",
  "text": "Was this page helpful?\nThanks for the feedback. If you have a specific, answerable question about how to use Kubernetes, ask it on\nStack Overflow\n.\nOpen an issue in the\nGitHub Repository\nif you want to\nreport a problem\nor\nsuggest an improvement\n."
}