{
  "id": "14896bc1ba3f29cd8e670434a777af68",
  "source": "k8s_docs",
  "title": "Running ZooKeeper, A Distributed System Coordinator — Feedback",
  "source_url": "https://kubernetes.io/docs/tutorials/stateful-application/zookeeper/#feedback",
  "text": "Was this page helpful?\nThanks for the feedback. If you have a specific, answerable question about how to use Kubernetes, ask it on\nStack Overflow\n.\nOpen an issue in the\nGitHub Repository\nif you want to\nreport a problem\nor\nsuggest an improvement\n."
}