{
  "id": "1e3ede5184424cb2b9fd9582247b7121",
  "source": "k8s_docs",
  "title": "Set Up DRA in a Cluster — Verify that DRA is enabled",
  "source_url": "https://kubernetes.io/docs/tasks/configure-pod-container/assign-resources/set-up-dra-cluster/#verify",
  "text": "To verify that the cluster is configured correctly, try to list DeviceClasses:\nkubectl get deviceclasses\nIf the component configuration was correct, the output is similar to the\nfollowing:\nNo resources found\nIf DRA isn't correctly configured, the output of the preceding command is\nsimilar to the following:\nerror: the server doesn't have a resource type \"deviceclasses\"\nFor example, this can occur when the resource.k8s.io API group was disabled.\nA similar check is applicable to alpha or beta quality top-level types.\nTry the following troubleshooting steps:\nReconfigure and restart the\nkube-apiserver\ncomponent.\nIf the complete\n.spec.resourceClaims\nfield gets removed from Pods, or if\nPods get scheduled without considering the ResourceClaims, then verify\nthat the\nDynamicResourceAllocation\nfeature gate\nis not turned off\nfor kube-apiserver, kube-controller-manager, kube-scheduler or the kubelet.\nReconfigure and restart the\nkube-apiserver\ncomponent.\nIf the complete\n.spec.resourceClaims\nfield gets removed from Pods, or if\nPods get scheduled without considering the ResourceClaims, then verify\nthat the\nDynamicResourceAllocation\nfeature gate\nis not turned off\nfor kube-apiserver, kube-controller-manager, kube-scheduler or the kubelet."
}